odoo/addons/website_sale_product_attribute_filter_category/README.rst
odoo/addons/website_sale_product_attribute_filter_category/__init__.py
odoo/addons/website_sale_product_attribute_filter_category/__manifest__.py
odoo/addons/website_sale_product_attribute_filter_category/controllers/__init__.py
odoo/addons/website_sale_product_attribute_filter_category/controllers/main.py
odoo/addons/website_sale_product_attribute_filter_category/i18n/es.po
odoo/addons/website_sale_product_attribute_filter_category/i18n/es_AR.po
odoo/addons/website_sale_product_attribute_filter_category/i18n/fi.po
odoo/addons/website_sale_product_attribute_filter_category/i18n/it.po
odoo/addons/website_sale_product_attribute_filter_category/i18n/nl.po
odoo/addons/website_sale_product_attribute_filter_category/i18n/website_sale_product_attribute_filter_category.pot
odoo/addons/website_sale_product_attribute_filter_category/models/__init__.py
odoo/addons/website_sale_product_attribute_filter_category/models/product_attribute_category.py
odoo/addons/website_sale_product_attribute_filter_category/readme/CONFIGURE.rst
odoo/addons/website_sale_product_attribute_filter_category/readme/CONTRIBUTORS.rst
odoo/addons/website_sale_product_attribute_filter_category/readme/DESCRIPTION.rst
odoo/addons/website_sale_product_attribute_filter_category/readme/USAGE.rst
odoo/addons/website_sale_product_attribute_filter_category/static/description/icon.png
odoo/addons/website_sale_product_attribute_filter_category/static/description/index.html
odoo/addons/website_sale_product_attribute_filter_category/static/src/scss/website_sale_product_attribute_filter_category.scss
odoo/addons/website_sale_product_attribute_filter_category/static/tests/tours/website_sale_product_attribute_filter_category.js
odoo/addons/website_sale_product_attribute_filter_category/tests/__init__.py
odoo/addons/website_sale_product_attribute_filter_category/tests/test_website_sale_product_attribute_filter_category.py
odoo14_addon_website_sale_product_attribute_filter_category-14.0.1.0.1.dev12.dist-info/METADATA
odoo14_addon_website_sale_product_attribute_filter_category-14.0.1.0.1.dev12.dist-info/WHEEL
odoo14_addon_website_sale_product_attribute_filter_category-14.0.1.0.1.dev12.dist-info/top_level.txt
odoo14_addon_website_sale_product_attribute_filter_category-14.0.1.0.1.dev12.dist-info/RECORD
